<?xml version="1.0" encoding="UTF-8"?>
<con:soapui-project id="9b4eb200-30de-4516-b137-52c3560ab8fe" activeEnvironment="Default" name="Bibliotheque" resourceRoot="" soapui-version="5.5.0" xmlns:con="http://eviware.com/soapui/config"><con:settings/><con:interface xsi:type="con:WsdlInterface" id="1eb2c1e3-1164-4830-aec7-e92b20a37e32" wsaVersion="NONE" name="BibliothequeServicesPortBinding" type="wsdl" bindingName="{http://biblio.com/}BibliothequeServicesPortBinding" soapVersion="1_1" anonymous="optional" definition="http://localhost:8084/bibliotheque/bibliothequeB?wsdl" xmlns:xsi="http://www.w3.org/2001/XMLSchema-instance"><con:settings/><con:definitionCache type="TEXT" rootPart="http://localhost:8084/bibliotheque/bibliothequeB?wsdl"><con:part><con:url>http://localhost:8084/bibliotheque/bibliothequeB?wsdl</con:url><con:content><![CDATA[<!--Published by JAX-WS RI (http://jax-ws.java.net). RI's version is JAX-WS RI 2.3.0 svn-revision#3528ea595bd29309f69172d231bbce272d21035c.-->
<!--Generated by JAX-WS RI (http://javaee.github.io/metro-jax-ws). RI's version is JAX-WS RI 2.3.0 svn-revision#3528ea595bd29309f69172d231bbce272d21035c.-->
<definitions targetNamespace="http://biblio.com/" name="BibliothequeServicesService" xmlns:wsu="http://docs.oasis-open.org/wss/2004/01/oasis-200401-wss-wssecurity-utility-1.0.xsd" xmlns:wsp="http://www.w3.org/ns/ws-policy" xmlns:wsp1_2="http://schemas.xmlsoap.org/ws/2004/09/policy" xmlns:wsam="http://www.w3.org/2007/05/addressing/metadata" xmlns:soap="http://schemas.xmlsoap.org/wsdl/soap/" xmlns:tns="http://biblio.com/" xmlns:xsd="http://www.w3.org/2001/XMLSchema" xmlns="http://schemas.xmlsoap.org/wsdl/">
  <types>
    <xsd:schema>
      <xsd:import namespace="http://biblio.com/" schemaLocation="http://localhost:8084/bibliotheque/bibliothequeB?xsd=1"/>
    </xsd:schema>
  </types>
  <message name="addBiblio">
    <part name="parameters" element="tns:addBiblio"/>
  </message>
  <message name="addBiblioResponse">
    <part name="parameters" element="tns:addBiblioResponse"/>
  </message>
  <message name="listDocument">
    <part name="parameters" element="tns:listDocument"/>
  </message>
  <message name="listDocumentResponse">
    <part name="parameters" element="tns:listDocumentResponse"/>
  </message>
  <message name="searchBiblio">
    <part name="parameters" element="tns:searchBiblio"/>
  </message>
  <message name="searchBiblioResponse">
    <part name="parameters" element="tns:searchBiblioResponse"/>
  </message>
  <message name="addDocument">
    <part name="parameters" element="tns:addDocument"/>
  </message>
  <message name="addDocumentResponse">
    <part name="parameters" element="tns:addDocumentResponse"/>
  </message>
  <message name="addPret">
    <part name="parameters" element="tns:addPret"/>
  </message>
  <message name="addPretResponse">
    <part name="parameters" element="tns:addPretResponse"/>
  </message>
  <message name="deletePret">
    <part name="parameters" element="tns:deletePret"/>
  </message>
  <message name="deletePretResponse">
    <part name="parameters" element="tns:deletePretResponse"/>
  </message>
  <message name="doLoginClient">
    <part name="parameters" element="tns:doLoginClient"/>
  </message>
  <message name="doLoginClientResponse">
    <part name="parameters" element="tns:doLoginClientResponse"/>
  </message>
  <message name="doLogin">
    <part name="parameters" element="tns:doLogin"/>
  </message>
  <message name="doLoginResponse">
    <part name="parameters" element="tns:doLoginResponse"/>
  </message>
  <message name="deleteClient">
    <part name="parameters" element="tns:deleteClient"/>
  </message>
  <message name="deleteClientResponse">
    <part name="parameters" element="tns:deleteClientResponse"/>
  </message>
  <message name="listInfoDocument">
    <part name="parameters" element="tns:listInfoDocument"/>
  </message>
  <message name="listInfoDocumentResponse">
    <part name="parameters" element="tns:listInfoDocumentResponse"/>
  </message>
  <message name="addClient">
    <part name="parameters" element="tns:addClient"/>
  </message>
  <message name="addClientResponse">
    <part name="parameters" element="tns:addClientResponse"/>
  </message>
  <message name="addUser">
    <part name="parameters" element="tns:addUser"/>
  </message>
  <message name="addUserResponse">
    <part name="parameters" element="tns:addUserResponse"/>
  </message>
  <message name="searchPret">
    <part name="parameters" element="tns:searchPret"/>
  </message>
  <message name="searchPretResponse">
    <part name="parameters" element="tns:searchPretResponse"/>
  </message>
  <message name="listPret">
    <part name="parameters" element="tns:listPret"/>
  </message>
  <message name="listPretResponse">
    <part name="parameters" element="tns:listPretResponse"/>
  </message>
  <message name="deleteUser">
    <part name="parameters" element="tns:deleteUser"/>
  </message>
  <message name="deleteUserResponse">
    <part name="parameters" element="tns:deleteUserResponse"/>
  </message>
  <message name="updatePret">
    <part name="parameters" element="tns:updatePret"/>
  </message>
  <message name="updatePretResponse">
    <part name="parameters" element="tns:updatePretResponse"/>
  </message>
  <message name="listClient">
    <part name="parameters" element="tns:listClient"/>
  </message>
  <message name="listClientResponse">
    <part name="parameters" element="tns:listClientResponse"/>
  </message>
  <portType name="BibliothequeServices">
    <operation name="addBiblio">
      <input wsam:Action="http://biblio.com/BibliothequeServices/addBiblioRequest" message="tns:addBiblio"/>
      <output wsam:Action="http://biblio.com/BibliothequeServices/addBiblioResponse" message="tns:addBiblioResponse"/>
    </operation>
    <operation name="listDocument">
      <input wsam:Action="http://biblio.com/BibliothequeServices/listDocumentRequest" message="tns:listDocument"/>
      <output wsam:Action="http://biblio.com/BibliothequeServices/listDocumentResponse" message="tns:listDocumentResponse"/>
    </operation>
    <operation name="searchBiblio">
      <input wsam:Action="http://biblio.com/BibliothequeServices/searchBiblioRequest" message="tns:searchBiblio"/>
      <output wsam:Action="http://biblio.com/BibliothequeServices/searchBiblioResponse" message="tns:searchBiblioResponse"/>
    </operation>
    <operation name="addDocument">
      <input wsam:Action="http://biblio.com/BibliothequeServices/addDocumentRequest" message="tns:addDocument"/>
      <output wsam:Action="http://biblio.com/BibliothequeServices/addDocumentResponse" message="tns:addDocumentResponse"/>
    </operation>
    <operation name="addPret">
      <input wsam:Action="http://biblio.com/BibliothequeServices/addPretRequest" message="tns:addPret"/>
      <output wsam:Action="http://biblio.com/BibliothequeServices/addPretResponse" message="tns:addPretResponse"/>
    </operation>
    <operation name="deletePret">
      <input wsam:Action="http://biblio.com/BibliothequeServices/deletePretRequest" message="tns:deletePret"/>
      <output wsam:Action="http://biblio.com/BibliothequeServices/deletePretResponse" message="tns:deletePretResponse"/>
    </operation>
    <operation name="doLoginClient">
      <input wsam:Action="http://biblio.com/BibliothequeServices/doLoginClientRequest" message="tns:doLoginClient"/>
      <output wsam:Action="http://biblio.com/BibliothequeServices/doLoginClientResponse" message="tns:doLoginClientResponse"/>
    </operation>
    <operation name="doLogin">
      <input wsam:Action="http://biblio.com/BibliothequeServices/doLoginRequest" message="tns:doLogin"/>
      <output wsam:Action="http://biblio.com/BibliothequeServices/doLoginResponse" message="tns:doLoginResponse"/>
    </operation>
    <operation name="deleteClient">
      <input wsam:Action="http://biblio.com/BibliothequeServices/deleteClientRequest" message="tns:deleteClient"/>
      <output wsam:Action="http://biblio.com/BibliothequeServices/deleteClientResponse" message="tns:deleteClientResponse"/>
    </operation>
    <operation name="listInfoDocument">
      <input wsam:Action="http://biblio.com/BibliothequeServices/listInfoDocumentRequest" message="tns:listInfoDocument"/>
      <output wsam:Action="http://biblio.com/BibliothequeServices/listInfoDocumentResponse" message="tns:listInfoDocumentResponse"/>
    </operation>
    <operation name="addClient">
      <input wsam:Action="http://biblio.com/BibliothequeServices/addClientRequest" message="tns:addClient"/>
      <output wsam:Action="http://biblio.com/BibliothequeServices/addClientResponse" message="tns:addClientResponse"/>
    </operation>
    <operation name="addUser">
      <input wsam:Action="http://biblio.com/BibliothequeServices/addUserRequest" message="tns:addUser"/>
      <output wsam:Action="http://biblio.com/BibliothequeServices/addUserResponse" message="tns:addUserResponse"/>
    </operation>
    <operation name="searchPret">
      <input wsam:Action="http://biblio.com/BibliothequeServices/searchPretRequest" message="tns:searchPret"/>
      <output wsam:Action="http://biblio.com/BibliothequeServices/searchPretResponse" message="tns:searchPretResponse"/>
    </operation>
    <operation name="listPret">
      <input wsam:Action="http://biblio.com/BibliothequeServices/listPretRequest" message="tns:listPret"/>
      <output wsam:Action="http://biblio.com/BibliothequeServices/listPretResponse" message="tns:listPretResponse"/>
    </operation>
    <operation name="deleteUser">
      <input wsam:Action="http://biblio.com/BibliothequeServices/deleteUserRequest" message="tns:deleteUser"/>
      <output wsam:Action="http://biblio.com/BibliothequeServices/deleteUserResponse" message="tns:deleteUserResponse"/>
    </operation>
    <operation name="updatePret">
      <input wsam:Action="http://biblio.com/BibliothequeServices/updatePretRequest" message="tns:updatePret"/>
      <output wsam:Action="http://biblio.com/BibliothequeServices/updatePretResponse" message="tns:updatePretResponse"/>
    </operation>
    <operation name="listClient">
      <input wsam:Action="http://biblio.com/BibliothequeServices/listClientRequest" message="tns:listClient"/>
      <output wsam:Action="http://biblio.com/BibliothequeServices/listClientResponse" message="tns:listClientResponse"/>
    </operation>
  </portType>
  <binding name="BibliothequeServicesPortBinding" type="tns:BibliothequeServices">
    <soap:binding transport="http://schemas.xmlsoap.org/soap/http" style="document"/>
    <operation name="addBiblio">
      <soap:operation soapAction=""/>
      <input>
        <soap:body use="literal"/>
      </input>
      <output>
        <soap:body use="literal"/>
      </output>
    </operation>
    <operation name="listDocument">
      <soap:operation soapAction=""/>
      <input>
        <soap:body use="literal"/>
      </input>
      <output>
        <soap:body use="literal"/>
      </output>
    </operation>
    <operation name="searchBiblio">
      <soap:operation soapAction=""/>
      <input>
        <soap:body use="literal"/>
      </input>
      <output>
        <soap:body use="literal"/>
      </output>
    </operation>
    <operation name="addDocument">
      <soap:operation soapAction=""/>
      <input>
        <soap:body use="literal"/>
      </input>
      <output>
        <soap:body use="literal"/>
      </output>
    </operation>
    <operation name="addPret">
      <soap:operation soapAction=""/>
      <input>
        <soap:body use="literal"/>
      </input>
      <output>
        <soap:body use="literal"/>
      </output>
    </operation>
    <operation name="deletePret">
      <soap:operation soapAction=""/>
      <input>
        <soap:body use="literal"/>
      </input>
      <output>
        <soap:body use="literal"/>
      </output>
    </operation>
    <operation name="doLoginClient">
      <soap:operation soapAction=""/>
      <input>
        <soap:body use="literal"/>
      </input>
      <output>
        <soap:body use="literal"/>
      </output>
    </operation>
    <operation name="doLogin">
      <soap:operation soapAction=""/>
      <input>
        <soap:body use="literal"/>
      </input>
      <output>
        <soap:body use="literal"/>
      </output>
    </operation>
    <operation name="deleteClient">
      <soap:operation soapAction=""/>
      <input>
        <soap:body use="literal"/>
      </input>
      <output>
        <soap:body use="literal"/>
      </output>
    </operation>
    <operation name="listInfoDocument">
      <soap:operation soapAction=""/>
      <input>
        <soap:body use="literal"/>
      </input>
      <output>
        <soap:body use="literal"/>
      </output>
    </operation>
    <operation name="addClient">
      <soap:operation soapAction=""/>
      <input>
        <soap:body use="literal"/>
      </input>
      <output>
        <soap:body use="literal"/>
      </output>
    </operation>
    <operation name="addUser">
      <soap:operation soapAction=""/>
      <input>
        <soap:body use="literal"/>
      </input>
      <output>
        <soap:body use="literal"/>
      </output>
    </operation>
    <operation name="searchPret">
      <soap:operation soapAction=""/>
      <input>
        <soap:body use="literal"/>
      </input>
      <output>
        <soap:body use="literal"/>
      </output>
    </operation>
    <operation name="listPret">
      <soap:operation soapAction=""/>
      <input>
        <soap:body use="literal"/>
      </input>
      <output>
        <soap:body use="literal"/>
      </output>
    </operation>
    <operation name="deleteUser">
      <soap:operation soapAction=""/>
      <input>
        <soap:body use="literal"/>
      </input>
      <output>
        <soap:body use="literal"/>
      </output>
    </operation>
    <operation name="updatePret">
      <soap:operation soapAction=""/>
      <input>
        <soap:body use="literal"/>
      </input>
      <output>
        <soap:body use="literal"/>
      </output>
    </operation>
    <operation name="listClient">
      <soap:operation soapAction=""/>
      <input>
        <soap:body use="literal"/>
      </input>
      <output>
        <soap:body use="literal"/>
      </output>
    </operation>
  </binding>
  <service name="BibliothequeServicesService">
    <port name="BibliothequeServicesPort" binding="tns:BibliothequeServicesPortBinding">
      <soap:address location="http://localhost:8084/bibliotheque/bibliothequeB"/>
    </port>
  </service>
</definitions>]]></con:content><con:type>http://schemas.xmlsoap.org/wsdl/</con:type></con:part><con:part><con:url>http://localhost:8084/bibliotheque/bibliothequeB?xsd=1</con:url><con:content><![CDATA[<!--Published by JAX-WS RI (http://jax-ws.java.net). RI's version is JAX-WS RI 2.3.0 svn-revision#3528ea595bd29309f69172d231bbce272d21035c.-->
<xs:schema version="1.0" targetNamespace="http://biblio.com/" xmlns:tns="http://biblio.com/" xmlns:xs="http://www.w3.org/2001/XMLSchema">
  <xs:element name="BibliothequeResponse" type="tns:BibliothequeResponse"/>
  <xs:element name="ClientResponse" type="tns:ClientResponse"/>
  <xs:element name="DocumentResponse" type="tns:DocumentResponse"/>
  <xs:element name="InfoPretResponse" type="tns:InfoPretResponse"/>
  <xs:element name="PretResponse" type="tns:PretResponse"/>
  <xs:element name="UtilisateurResponse" type="tns:UtilisateurResponse"/>
  <xs:element name="addBiblio" type="tns:addBiblio"/>
  <xs:element name="addBiblioResponse" type="tns:addBiblioResponse"/>
  <xs:element name="addClient" type="tns:addClient"/>
  <xs:element name="addClientResponse" type="tns:addClientResponse"/>
  <xs:element name="addDocument" type="tns:addDocument"/>
  <xs:element name="addDocumentResponse" type="tns:addDocumentResponse"/>
  <xs:element name="addPret" type="tns:addPret"/>
  <xs:element name="addPretResponse" type="tns:addPretResponse"/>
  <xs:element name="addUser" type="tns:addUser"/>
  <xs:element name="addUserResponse" type="tns:addUserResponse"/>
  <xs:element name="deleteClient" type="tns:deleteClient"/>
  <xs:element name="deleteClientResponse" type="tns:deleteClientResponse"/>
  <xs:element name="deletePret" type="tns:deletePret"/>
  <xs:element name="deletePretResponse" type="tns:deletePretResponse"/>
  <xs:element name="deleteUser" type="tns:deleteUser"/>
  <xs:element name="deleteUserResponse" type="tns:deleteUserResponse"/>
  <xs:element name="doLogin" type="tns:doLogin"/>
  <xs:element name="doLoginClient" type="tns:doLoginClient"/>
  <xs:element name="doLoginClientResponse" type="tns:doLoginClientResponse"/>
  <xs:element name="doLoginResponse" type="tns:doLoginResponse"/>
  <xs:element name="listClient" type="tns:listClient"/>
  <xs:element name="listClientResponse" type="tns:listClientResponse"/>
  <xs:element name="listDocument" type="tns:listDocument"/>
  <xs:element name="listDocumentResponse" type="tns:listDocumentResponse"/>
  <xs:element name="listInfoDocument" type="tns:listInfoDocument"/>
  <xs:element name="listInfoDocumentResponse" type="tns:listInfoDocumentResponse"/>
  <xs:element name="listPret" type="tns:listPret"/>
  <xs:element name="listPretResponse" type="tns:listPretResponse"/>
  <xs:element name="searchBiblio" type="tns:searchBiblio"/>
  <xs:element name="searchBiblioResponse" type="tns:searchBiblioResponse"/>
  <xs:element name="searchPret" type="tns:searchPret"/>
  <xs:element name="searchPretResponse" type="tns:searchPretResponse"/>
  <xs:element name="updatePret" type="tns:updatePret"/>
  <xs:element name="updatePretResponse" type="tns:updatePretResponse"/>
  <xs:complexType name="updatePret">
    <xs:sequence>
      <xs:element name="dureepret" type="xs:string" minOccurs="0"/>
      <xs:element name="prolonger" type="xs:boolean"/>
      <xs:element name="cloturationpret" type="xs:boolean"/>
      <xs:element name="refpret" type="xs:int"/>
    </xs:sequence>
  </xs:complexType>
  <xs:complexType name="updatePretResponse">
    <xs:sequence>
      <xs:element name="return" type="tns:PretResponse" minOccurs="0"/>
    </xs:sequence>
  </xs:complexType>
  <xs:complexType name="PretResponse">
    <xs:sequence>
      <xs:element name="cloturationpret" type="xs:boolean"/>
      <xs:element name="datefinpret" type="xs:dateTime" minOccurs="0"/>
      <xs:element name="datepret" type="xs:dateTime" minOccurs="0"/>
      <xs:element name="dureePret" type="xs:string" minOccurs="0"/>
      <xs:element name="nbrexemplaire" type="xs:string" minOccurs="0"/>
      <xs:element name="prolonger" type="xs:boolean"/>
      <xs:element name="refclient" type="xs:int"/>
      <xs:element name="refouvrage" type="xs:int"/>
      <xs:element name="refpret" type="xs:int"/>
    </xs:sequence>
  </xs:complexType>
  <xs:complexType name="addBiblio">
    <xs:sequence>
      <xs:element name="refbibliotheque" type="xs:int"/>
      <xs:element name="nom" type="xs:string" minOccurs="0"/>
      <xs:element name="adresse" type="xs:string" minOccurs="0"/>
      <xs:element name="ville" type="xs:string" minOccurs="0"/>
      <xs:element name="codepostal" type="xs:string" minOccurs="0"/>
      <xs:element name="description" type="xs:string" minOccurs="0"/>
    </xs:sequence>
  </xs:complexType>
  <xs:complexType name="addBiblioResponse">
    <xs:sequence>
      <xs:element name="return" type="tns:BibliothequeResponse" minOccurs="0"/>
    </xs:sequence>
  </xs:complexType>
  <xs:complexType name="BibliothequeResponse">
    <xs:sequence>
      <xs:element name="adresse" type="xs:string" minOccurs="0"/>
      <xs:element name="codepostal" type="xs:string" minOccurs="0"/>
      <xs:element name="description" type="xs:string" minOccurs="0"/>
      <xs:element name="nom" type="xs:string" minOccurs="0"/>
      <xs:element name="refbibliotheque" type="xs:int"/>
      <xs:element name="ville" type="xs:string" minOccurs="0"/>
    </xs:sequence>
  </xs:complexType>
  <xs:complexType name="listInfoDocument">
    <xs:sequence/>
  </xs:complexType>
  <xs:complexType name="listInfoDocumentResponse">
    <xs:sequence>
      <xs:element name="listInfoDocument" type="tns:InfoPretResponse" minOccurs="0" maxOccurs="unbounded"/>
    </xs:sequence>
  </xs:complexType>
  <xs:complexType name="InfoPretResponse">
    <xs:sequence>
      <xs:element name="datefinpret" type="xs:dateTime" minOccurs="0"/>
      <xs:element name="email" type="xs:string" minOccurs="0"/>
      <xs:element name="nomouvrage" type="xs:string" minOccurs="0"/>
    </xs:sequence>
  </xs:complexType>
  <xs:complexType name="deletePret">
    <xs:sequence>
      <xs:element name="dureepret" type="xs:string" minOccurs="0"/>
      <xs:element name="refpret" type="xs:int"/>
    </xs:sequence>
  </xs:complexType>
  <xs:complexType name="deletePretResponse">
    <xs:sequence>
      <xs:element name="return" type="tns:PretResponse" minOccurs="0"/>
    </xs:sequence>
  </xs:complexType>
  <xs:complexType name="addClient">
    <xs:sequence>
      <xs:element name="refbibliotheque" type="xs:int"/>
      <xs:element name="nom" type="xs:string" minOccurs="0"/>
      <xs:element name="prenom" type="xs:string" minOccurs="0"/>
      <xs:element name="sexe" type="xs:string" minOccurs="0"/>
      <xs:element name="pseudo" type="xs:string" minOccurs="0"/>
      <xs:element name="motPasse" type="xs:string" minOccurs="0"/>
      <xs:element name="adresse" type="xs:string" minOccurs="0"/>
      <xs:element name="email" type="xs:string" minOccurs="0"/>
      <xs:element name="codepostal" type="xs:string" minOccurs="0"/>
    </xs:sequence>
  </xs:complexType>
  <xs:complexType name="addClientResponse">
    <xs:sequence>
      <xs:element name="return" type="tns:ClientResponse" minOccurs="0"/>
    </xs:sequence>
  </xs:complexType>
  <xs:complexType name="ClientResponse">
    <xs:sequence>
      <xs:element name="adresse" type="xs:string" minOccurs="0"/>
      <xs:element name="codepostal" type="xs:string" minOccurs="0"/>
      <xs:element name="email" type="xs:string" minOccurs="0"/>
      <xs:element name="motpasse" type="xs:string" minOccurs="0"/>
      <xs:element name="nom" type="xs:string" minOccurs="0"/>
      <xs:element name="prenom" type="xs:string" minOccurs="0"/>
      <xs:element name="pseudo" type="xs:string" minOccurs="0"/>
      <xs:element name="refbibliotheque" type="xs:int"/>
      <xs:element name="refclient" type="xs:int"/>
      <xs:element name="sexe" type="xs:string" minOccurs="0"/>
    </xs:sequence>
  </xs:complexType>
  <xs:complexType name="listPret">
    <xs:sequence/>
  </xs:complexType>
  <xs:complexType name="listPretResponse">
    <xs:sequence>
      <xs:element name="listPret" type="tns:PretResponse" minOccurs="0" maxOccurs="unbounded"/>
    </xs:sequence>
  </xs:complexType>
  <xs:complexType name="doLoginClient">
    <xs:sequence>
      <xs:element name="pseudo" type="xs:string" minOccurs="0"/>
      <xs:element name="motpasse" type="xs:string" minOccurs="0"/>
    </xs:sequence>
  </xs:complexType>
  <xs:complexType name="doLoginClientResponse">
    <xs:sequence>
      <xs:element name="return" type="tns:ClientResponse" minOccurs="0"/>
    </xs:sequence>
  </xs:complexType>
  <xs:complexType name="deleteUser">
    <xs:sequence>
      <xs:element name="idutilisateur" type="xs:int"/>
    </xs:sequence>
  </xs:complexType>
  <xs:complexType name="deleteUserResponse">
    <xs:sequence>
      <xs:element name="return" type="tns:UtilisateurResponse" minOccurs="0"/>
    </xs:sequence>
  </xs:complexType>
  <xs:complexType name="UtilisateurResponse">
    <xs:sequence>
      <xs:element name="email" type="xs:string" minOccurs="0"/>
      <xs:element name="idutilisateur" type="xs:int"/>
      <xs:element name="motpasse" type="xs:string" minOccurs="0"/>
      <xs:element name="nom" type="xs:string" minOccurs="0"/>
      <xs:element name="prenom" type="xs:string" minOccurs="0"/>
      <xs:element name="pseudo" type="xs:string" minOccurs="0"/>
      <xs:element name="refbibliotheque" type="xs:int"/>
    </xs:sequence>
  </xs:complexType>
  <xs:complexType name="listDocument">
    <xs:sequence>
      <xs:element name="nomOuvrage" type="xs:string" minOccurs="0"/>
    </xs:sequence>
  </xs:complexType>
  <xs:complexType name="listDocumentResponse">
    <xs:sequence>
      <xs:element name="listDocument" type="tns:DocumentResponse" minOccurs="0" maxOccurs="unbounded"/>
    </xs:sequence>
  </xs:complexType>
  <xs:complexType name="DocumentResponse">
    <xs:sequence>
      <xs:element name="categorie" type="xs:string" minOccurs="0"/>
      <xs:element name="nombibliotheque" type="xs:string" minOccurs="0"/>
      <xs:element name="nomouvrage" type="xs:string" minOccurs="0"/>
      <xs:element name="quantitetotal" type="xs:string" minOccurs="0"/>
      <xs:element name="rayon" type="xs:string" minOccurs="0"/>
      <xs:element name="refbibliotheque" type="xs:int"/>
      <xs:element name="refouvrage" type="xs:int"/>
    </xs:sequence>
  </xs:complexType>
  <xs:complexType name="searchBiblio">
    <xs:sequence>
      <xs:element name="refbibliotheque" type="xs:int"/>
    </xs:sequence>
  </xs:complexType>
  <xs:complexType name="searchBiblioResponse">
    <xs:sequence>
      <xs:element name="return" type="tns:BibliothequeResponse" minOccurs="0"/>
    </xs:sequence>
  </xs:complexType>
  <xs:complexType name="addUser">
    <xs:sequence>
      <xs:element name="refbibliotheque" type="xs:int"/>
      <xs:element name="pseudo" type="xs:string" minOccurs="0"/>
      <xs:element name="motPasse" type="xs:string" minOccurs="0"/>
      <xs:element name="email" type="xs:string" minOccurs="0"/>
      <xs:element name="nom" type="xs:string" minOccurs="0"/>
      <xs:element name="prenom" type="xs:string" minOccurs="0"/>
    </xs:sequence>
  </xs:complexType>
  <xs:complexType name="addUserResponse">
    <xs:sequence>
      <xs:element name="return" type="tns:UtilisateurResponse" minOccurs="0"/>
    </xs:sequence>
  </xs:complexType>
  <xs:complexType name="listClient">
    <xs:sequence/>
  </xs:complexType>
  <xs:complexType name="listClientResponse">
    <xs:sequence>
      <xs:element name="listClient" type="tns:ClientResponse" minOccurs="0" maxOccurs="unbounded"/>
    </xs:sequence>
  </xs:complexType>
  <xs:complexType name="addDocument">
    <xs:sequence>
      <xs:element name="refbibliotheque" type="xs:int"/>
      <xs:element name="nombibliotheque" type="xs:string" minOccurs="0"/>
      <xs:element name="nomouvrage" type="xs:string" minOccurs="0"/>
      <xs:element name="categorie" type="xs:string" minOccurs="0"/>
      <xs:element name="rayon" type="xs:string" minOccurs="0"/>
      <xs:element name="quantitetotal" type="xs:string" minOccurs="0"/>
    </xs:sequence>
  </xs:complexType>
  <xs:complexType name="addDocumentResponse">
    <xs:sequence>
      <xs:element name="return" type="tns:DocumentResponse" minOccurs="0"/>
    </xs:sequence>
  </xs:complexType>
  <xs:complexType name="addPret">
    <xs:sequence>
      <xs:element name="refpret" type="xs:int"/>
      <xs:element name="refclient" type="xs:int"/>
      <xs:element name="refouvrage" type="xs:int"/>
      <xs:element name="dureepret" type="xs:string" minOccurs="0"/>
      <xs:element name="nbrexemplaire" type="xs:string" minOccurs="0"/>
      <xs:element name="prolonger" type="xs:boolean"/>
      <xs:element name="cloturationpret" type="xs:boolean"/>
    </xs:sequence>
  </xs:complexType>
  <xs:complexType name="addPretResponse">
    <xs:sequence>
      <xs:element name="return" type="tns:PretResponse" minOccurs="0"/>
    </xs:sequence>
  </xs:complexType>
  <xs:complexType name="doLogin">
    <xs:sequence>
      <xs:element name="pseudo" type="xs:string" minOccurs="0"/>
      <xs:element name="motPasse" type="xs:string" minOccurs="0"/>
    </xs:sequence>
  </xs:complexType>
  <xs:complexType name="doLoginResponse">
    <xs:sequence>
      <xs:element name="return" type="tns:UtilisateurResponse" minOccurs="0"/>
    </xs:sequence>
  </xs:complexType>
  <xs:complexType name="deleteClient">
    <xs:sequence>
      <xs:element name="refclient" type="xs:int"/>
    </xs:sequence>
  </xs:complexType>
  <xs:complexType name="deleteClientResponse">
    <xs:sequence>
      <xs:element name="return" type="tns:ClientResponse" minOccurs="0"/>
    </xs:sequence>
  </xs:complexType>
  <xs:complexType name="searchPret">
    <xs:sequence>
      <xs:element name="refpret" type="xs:int"/>
    </xs:sequence>
  </xs:complexType>
  <xs:complexType name="searchPretResponse">
    <xs:sequence>
      <xs:element name="return" type="tns:PretResponse" minOccurs="0"/>
    </xs:sequence>
  </xs:complexType>
</xs:schema>]]></con:content><con:type>http://www.w3.org/2001/XMLSchema</con:type></con:part></con:definitionCache><con:endpoints><con:endpoint>http://localhost:8084/bibliotheque/bibliothequeB</con:endpoint></con:endpoints><con:operation id="c9ce3560-74a7-42b2-9abb-7f12f6823942" isOneWay="false" action="" name="addBiblio" bindingOperationName="addBiblio" type="Request-Response" inputName="" receivesAttachments="false" sendsAttachments="false" anonymous="optional"><con:settings/><con:call id="dbe6df84-db73-417e-95cd-7de26576c23c" name="Request 1"><con:settings/><con:encoding>UTF-8</con:encoding><con:endpoint>http://localhost:8084/bibliotheque/bibliothequeB</con:endpoint><con:request><![CDATA[<soapenv:Envelope xmlns:soapenv="http://schemas.xmlsoap.org/soap/envelope/" xmlns:bib="http://biblio.com/">\r
   <soapenv:Header/>\r
   <soapenv:Body>\r
      <bib:addBiblio>\r
         <refbibliotheque>?</refbibliotheque>\r
         <!--Optional:-->\r
         <nom>?</nom>\r
         <!--Optional:-->\r
         <adresse>?</adresse>\r
         <!--Optional:-->\r
         <ville>?</ville>\r
         <!--Optional:-->\r
         <codepostal>?</codepostal>\r
         <!--Optional:-->\r
         <description>?</description>\r
      </bib:addBiblio>\r
   </soapenv:Body>\r
</soapenv:Envelope>]]></con:request><con:wsaConfig mustUnderstand="NONE" version="200508" action="http://biblio.com/BibliothequeServices/addBiblioRequest"/></con:call></con:operation><con:operation id="1b783ad5-4c70-4b16-9090-17ab80d4e183" isOneWay="false" action="" name="addClient" bindingOperationName="addClient" type="Request-Response" inputName="" receivesAttachments="false" sendsAttachments="false" anonymous="optional"><con:settings/><con:call id="8841ac8f-b2f3-43d9-80fe-9be38686db79" name="Request 1"><con:settings/><con:encoding>UTF-8</con:encoding><con:endpoint>http://localhost:8084/bibliotheque/bibliothequeB</con:endpoint><con:request><![CDATA[<soapenv:Envelope xmlns:soapenv="http://schemas.xmlsoap.org/soap/envelope/" xmlns:bib="http://biblio.com/">\r
   <soapenv:Header/>\r
   <soapenv:Body>\r
      <bib:addClient>\r
         <refbibliotheque>?</refbibliotheque>\r
         <!--Optional:-->\r
         <nom>?</nom>\r
         <!--Optional:-->\r
         <prenom>?</prenom>\r
         <!--Optional:-->\r
         <sexe>?</sexe>\r
         <!--Optional:-->\r
         <pseudo>?</pseudo>\r
         <!--Optional:-->\r
         <motPasse>?</motPasse>\r
         <!--Optional:-->\r
         <adresse>?</adresse>\r
         <!--Optional:-->\r
         <email>?</email>\r
         <!--Optional:-->\r
         <codepostal>?</codepostal>\r
      </bib:addClient>\r
   </soapenv:Body>\r
</soapenv:Envelope>]]></con:request><con:wsaConfig mustUnderstand="NONE" version="200508" action="http://biblio.com/BibliothequeServices/addClientRequest"/></con:call></con:operation><con:operation id="28f99a23-ff4b-4dd0-82fb-c4e19a5276a2" isOneWay="false" action="" name="addDocument" bindingOperationName="addDocument" type="Request-Response" inputName="" receivesAttachments="false" sendsAttachments="false" anonymous="optional"><con:settings/><con:call id="6d25efe8-039c-4808-a164-808ed30fdd63" name="Request 1"><con:settings/><con:encoding>UTF-8</con:encoding><con:endpoint>http://localhost:8084/bibliotheque/bibliothequeB</con:endpoint><con:request><![CDATA[<soapenv:Envelope xmlns:soapenv="http://schemas.xmlsoap.org/soap/envelope/" xmlns:bib="http://biblio.com/">\r
   <soapenv:Header/>\r
   <soapenv:Body>\r
      <bib:addDocument>\r
         <refbibliotheque>?</refbibliotheque>\r
         <!--Optional:-->\r
         <nombibliotheque>?</nombibliotheque>\r
         <!--Optional:-->\r
         <nomouvrage>?</nomouvrage>\r
         <!--Optional:-->\r
         <categorie>?</categorie>\r
         <!--Optional:-->\r
         <rayon>?</rayon>\r
         <!--Optional:-->\r
         <quantitetotal>?</quantitetotal>\r
      </bib:addDocument>\r
   </soapenv:Body>\r
</soapenv:Envelope>]]></con:request><con:wsaConfig mustUnderstand="NONE" version="200508" action="http://biblio.com/BibliothequeServices/addDocumentRequest"/></con:call></con:operation><con:operation id="18e0f5e4-f980-47ed-89d4-eee998ec83bc" isOneWay="false" action="" name="addPret" bindingOperationName="addPret" type="Request-Response" inputName="" receivesAttachments="false" sendsAttachments="false" anonymous="optional"><con:settings/><con:call id="7e46c376-ae64-4f72-acb0-474d4655cb32" name="Request 1"><con:settings/><con:encoding>UTF-8</con:encoding><con:endpoint>http://localhost:8084/bibliotheque/bibliothequeB</con:endpoint><con:request><![CDATA[<soapenv:Envelope xmlns:soapenv="http://schemas.xmlsoap.org/soap/envelope/" xmlns:bib="http://biblio.com/">\r
   <soapenv:Header/>\r
   <soapenv:Body>\r
      <bib:addPret>\r
         <refpret>?</refpret>\r
         <refclient>?</refclient>\r
         <refouvrage>?</refouvrage>\r
         <!--Optional:-->\r
         <dureepret>?</dureepret>\r
         <!--Optional:-->\r
         <nbrexemplaire>?</nbrexemplaire>\r
         <prolonger>?</prolonger>\r
         <cloturationpret>?</cloturationpret>\r
      </bib:addPret>\r
   </soapenv:Body>\r
</soapenv:Envelope>]]></con:request><con:wsaConfig mustUnderstand="NONE" version="200508" action="http://biblio.com/BibliothequeServices/addPretRequest"/></con:call></con:operation><con:operation id="74f25cf9-f2e9-433a-a956-5ec0892d8aa2" isOneWay="false" action="" name="addUser" bindingOperationName="addUser" type="Request-Response" inputName="" receivesAttachments="false" sendsAttachments="false" anonymous="optional"><con:settings/><con:call id="260201c8-e83d-4a5e-9a0b-5c2daae4ad23" name="Request 1"><con:settings/><con:encoding>UTF-8</con:encoding><con:endpoint>http://localhost:8084/bibliotheque/bibliothequeB</con:endpoint><con:request><![CDATA[<soapenv:Envelope xmlns:soapenv="http://schemas.xmlsoap.org/soap/envelope/" xmlns:bib="http://biblio.com/">\r
   <soapenv:Header/>\r
   <soapenv:Body>\r
      <bib:addUser>\r
         <refbibliotheque>?</refbibliotheque>\r
         <!--Optional:-->\r
         <pseudo>?</pseudo>\r
         <!--Optional:-->\r
         <motPasse>?</motPasse>\r
         <!--Optional:-->\r
         <email>?</email>\r
         <!--Optional:-->\r
         <nom>?</nom>\r
         <!--Optional:-->\r
         <prenom>?</prenom>\r
      </bib:addUser>\r
   </soapenv:Body>\r
</soapenv:Envelope>]]></con:request><con:wsaConfig mustUnderstand="NONE" version="200508" action="http://biblio.com/BibliothequeServices/addUserRequest"/></con:call></con:operation><con:operation id="f7d7c75b-5b78-48e1-bff3-b6711a6d2218" isOneWay="false" action="" name="deleteClient" bindingOperationName="deleteClient" type="Request-Response" inputName="" receivesAttachments="false" sendsAttachments="false" anonymous="optional"><con:settings/><con:call id="eb599cb4-0bb7-4890-af37-2c2ef9d18ac0" name="Request 1"><con:settings/><con:encoding>UTF-8</con:encoding><con:endpoint>http://localhost:8084/bibliotheque/bibliothequeB</con:endpoint><con:request><![CDATA[<soapenv:Envelope xmlns:soapenv="http://schemas.xmlsoap.org/soap/envelope/" xmlns:bib="http://biblio.com/">\r
   <soapenv:Header/>\r
   <soapenv:Body>\r
      <bib:deleteClient>\r
         <refclient>?</refclient>\r
      </bib:deleteClient>\r
   </soapenv:Body>\r
</soapenv:Envelope>]]></con:request><con:wsaConfig mustUnderstand="NONE" version="200508" action="http://biblio.com/BibliothequeServices/deleteClientRequest"/></con:call></con:operation><con:operation id="67e92a3d-533c-4189-9592-f6d5edb866e0" isOneWay="false" action="" name="deletePret" bindingOperationName="deletePret" type="Request-Response" inputName="" receivesAttachments="false" sendsAttachments="false" anonymous="optional"><con:settings/><con:call id="47a20ef4-5c35-4b81-84af-d037ba48b645" name="Request 1"><con:settings/><con:encoding>UTF-8</con:encoding><con:endpoint>http://localhost:8084/bibliotheque/bibliothequeB</con:endpoint><con:request><![CDATA[<soapenv:Envelope xmlns:soapenv="http://schemas.xmlsoap.org/soap/envelope/" xmlns:bib="http://biblio.com/">\r
   <soapenv:Header/>\r
   <soapenv:Body>\r
      <bib:deletePret>\r
         <!--Optional:-->\r
         <dureepret>?</dureepret>\r
         <refpret>?</refpret>\r
      </bib:deletePret>\r
   </soapenv:Body>\r
</soapenv:Envelope>]]></con:request><con:wsaConfig mustUnderstand="NONE" version="200508" action="http://biblio.com/BibliothequeServices/deletePretRequest"/></con:call></con:operation><con:operation id="f77ea5b8-154d-494f-a7ad-5c7c544d9b84" isOneWay="false" action="" name="deleteUser" bindingOperationName="deleteUser" type="Request-Response" inputName="" receivesAttachments="false" sendsAttachments="false" anonymous="optional"><con:settings/><con:call id="9d4ec3ea-0548-4fd1-a10a-845428a9c136" name="Request 1"><con:settings/><con:encoding>UTF-8</con:encoding><con:endpoint>http://localhost:8084/bibliotheque/bibliothequeB</con:endpoint><con:request><![CDATA[<soapenv:Envelope xmlns:soapenv="http://schemas.xmlsoap.org/soap/envelope/" xmlns:bib="http://biblio.com/">\r
   <soapenv:Header/>\r
   <soapenv:Body>\r
      <bib:deleteUser>\r
         <idutilisateur>?</idutilisateur>\r
      </bib:deleteUser>\r
   </soapenv:Body>\r
</soapenv:Envelope>]]></con:request><con:wsaConfig mustUnderstand="NONE" version="200508" action="http://biblio.com/BibliothequeServices/deleteUserRequest"/></con:call></con:operation><con:operation id="def9bcbc-22ed-460d-a610-0ee2bad143cf" isOneWay="false" action="" name="doLogin" bindingOperationName="doLogin" type="Request-Response" inputName="" receivesAttachments="false" sendsAttachments="false" anonymous="optional"><con:settings/><con:call id="69089c04-6aff-4c36-bea5-2c46af5968a9" name="Request 1"><con:settings/><con:encoding>UTF-8</con:encoding><con:endpoint>http://localhost:8084/bibliotheque/bibliothequeB</con:endpoint><con:request><![CDATA[<soapenv:Envelope xmlns:soapenv="http://schemas.xmlsoap.org/soap/envelope/" xmlns:bib="http://biblio.com/">\r
   <soapenv:Header/>\r
   <soapenv:Body>\r
      <bib:doLogin>\r
         <!--Optional:-->\r
         <pseudo>?</pseudo>\r
         <!--Optional:-->\r
         <motPasse>?</motPasse>\r
      </bib:doLogin>\r
   </soapenv:Body>\r
</soapenv:Envelope>]]></con:request><con:wsaConfig mustUnderstand="NONE" version="200508" action="http://biblio.com/BibliothequeServices/doLoginRequest"/></con:call></con:operation><con:operation id="a59c809e-a09b-4557-8751-45c9fde571d9" isOneWay="false" action="" name="doLoginClient" bindingOperationName="doLoginClient" type="Request-Response" inputName="" receivesAttachments="false" sendsAttachments="false" anonymous="optional"><con:settings/><con:call id="4487232a-cdce-41c1-a5e3-b5425f67ffd2" name="Request 1"><con:settings/><con:encoding>UTF-8</con:encoding><con:endpoint>http://localhost:8084/bibliotheque/bibliothequeB</con:endpoint><con:request><![CDATA[<soapenv:Envelope xmlns:soapenv="http://schemas.xmlsoap.org/soap/envelope/" xmlns:bib="http://biblio.com/">\r
   <soapenv:Header/>\r
   <soapenv:Body>\r
      <bib:doLoginClient>\r
         <!--Optional:-->\r
         <pseudo>?</pseudo>\r
         <!--Optional:-->\r
         <motpasse>?</motpasse>\r
      </bib:doLoginClient>\r
   </soapenv:Body>\r
</soapenv:Envelope>]]></con:request><con:wsaConfig mustUnderstand="NONE" version="200508" action="http://biblio.com/BibliothequeServices/doLoginClientRequest"/></con:call></con:operation><con:operation id="aa1c796a-93b7-4684-8a39-ea284981b188" isOneWay="false" action="" name="listClient" bindingOperationName="listClient" type="Request-Response" inputName="" receivesAttachments="false" sendsAttachments="false" anonymous="optional"><con:settings/><con:call id="c8258b86-1229-41a7-b89c-10b78ccc3d6d" name="Request 1"><con:settings/><con:encoding>UTF-8</con:encoding><con:endpoint>http://localhost:8084/bibliotheque/bibliothequeB</con:endpoint><con:request><![CDATA[<soapenv:Envelope xmlns:soapenv="http://schemas.xmlsoap.org/soap/envelope/" xmlns:bib="http://biblio.com/">\r
   <soapenv:Header/>\r
   <soapenv:Body>\r
      <bib:listClient/>\r
   </soapenv:Body>\r
</soapenv:Envelope>]]></con:request><con:wsaConfig mustUnderstand="NONE" version="200508" action="http://biblio.com/BibliothequeServices/listClientRequest"/></con:call></con:operation><con:operation id="2ac7cced-7bc5-4360-a67d-580dd99b77d2" isOneWay="false" action="" name="listDocument" bindingOperationName="listDocument" type="Request-Response" inputName="" receivesAttachments="false" sendsAttachments="false" anonymous="optional"><con:settings/><con:call id="044f1212-45de-435d-b180-c5418a3bb64b" name="Request 1"><con:settings/><con:encoding>UTF-8</con:encoding><con:endpoint>http://localhost:8084/bibliotheque/bibliothequeB</con:endpoint><con:request><![CDATA[<soapenv:Envelope xmlns:soapenv="http://schemas.xmlsoap.org/soap/envelope/" xmlns:bib="http://biblio.com/">\r
   <soapenv:Header/>\r
   <soapenv:Body>\r
      <bib:listDocument>\r
         <!--Optional:-->\r
         <nomOuvrage>?</nomOuvrage>\r
      </bib:listDocument>\r
   </soapenv:Body>\r
</soapenv:Envelope>]]></con:request><con:wsaConfig mustUnderstand="NONE" version="200508" action="http://biblio.com/BibliothequeServices/listDocumentRequest"/></con:call></con:operation><con:operation id="2d47b762-1ad1-4f0f-a53b-5af29f68cac3" isOneWay="false" action="" name="listInfoDocument" bindingOperationName="listInfoDocument" type="Request-Response" inputName="" receivesAttachments="false" sendsAttachments="false" anonymous="optional"><con:settings/><con:call id="54280f92-9b73-4672-9c29-6a93a31359d3" name="Request 1"><con:settings/><con:encoding>UTF-8</con:encoding><con:endpoint>http://localhost:8084/bibliotheque/bibliothequeB</con:endpoint><con:request><![CDATA[<soapenv:Envelope xmlns:soapenv="http://schemas.xmlsoap.org/soap/envelope/" xmlns:bib="http://biblio.com/">\r
   <soapenv:Header/>\r
   <soapenv:Body>\r
      <bib:listInfoDocument/>\r
   </soapenv:Body>\r
</soapenv:Envelope>]]></con:request><con:wsaConfig mustUnderstand="NONE" version="200508" action="http://biblio.com/BibliothequeServices/listInfoDocumentRequest"/></con:call></con:operation><con:operation id="4c9867e4-6646-455b-89ad-09f5bd9a34d7" isOneWay="false" action="" name="listPret" bindingOperationName="listPret" type="Request-Response" inputName="" receivesAttachments="false" sendsAttachments="false" anonymous="optional"><con:settings/><con:call id="46c7bd59-d4c7-49ab-9383-437cab399df7" name="Request 1"><con:settings/><con:encoding>UTF-8</con:encoding><con:endpoint>http://localhost:8084/bibliotheque/bibliothequeB</con:endpoint><con:request><![CDATA[<soapenv:Envelope xmlns:soapenv="http://schemas.xmlsoap.org/soap/envelope/" xmlns:bib="http://biblio.com/">\r
   <soapenv:Header/>\r
   <soapenv:Body>\r
      <bib:listPret/>\r
   </soapenv:Body>\r
</soapenv:Envelope>]]></con:request><con:wsaConfig mustUnderstand="NONE" version="200508" action="http://biblio.com/BibliothequeServices/listPretRequest"/></con:call></con:operation><con:operation id="f1b3c53d-269a-4147-8573-3d744c5ec765" isOneWay="false" action="" name="searchBiblio" bindingOperationName="searchBiblio" type="Request-Response" inputName="" receivesAttachments="false" sendsAttachments="false" anonymous="optional"><con:settings/><con:call id="f5d5c8ce-5465-4f76-b0c4-83dbb7b40332" name="Request 1"><con:settings/><con:encoding>UTF-8</con:encoding><con:endpoint>http://localhost:8084/bibliotheque/bibliothequeB</con:endpoint><con:request><![CDATA[<soapenv:Envelope xmlns:soapenv="http://schemas.xmlsoap.org/soap/envelope/" xmlns:bib="http://biblio.com/">\r
   <soapenv:Header/>\r
   <soapenv:Body>\r
      <bib:searchBiblio>\r
         <refbibliotheque>?</refbibliotheque>\r
      </bib:searchBiblio>\r
   </soapenv:Body>\r
</soapenv:Envelope>]]></con:request><con:wsaConfig mustUnderstand="NONE" version="200508" action="http://biblio.com/BibliothequeServices/searchBiblioRequest"/></con:call></con:operation><con:operation id="f0ef68a7-bc89-4abc-b57e-5429178fdae8" isOneWay="false" action="" name="searchPret" bindingOperationName="searchPret" type="Request-Response" inputName="" receivesAttachments="false" sendsAttachments="false" anonymous="optional"><con:settings/><con:call id="740565af-fe5f-4346-a407-980e5241d0d6" name="Request 1"><con:settings/><con:encoding>UTF-8</con:encoding><con:endpoint>http://localhost:8084/bibliotheque/bibliothequeB</con:endpoint><con:request><![CDATA[<soapenv:Envelope xmlns:soapenv="http://schemas.xmlsoap.org/soap/envelope/" xmlns:bib="http://biblio.com/">\r
   <soapenv:Header/>\r
   <soapenv:Body>\r
      <bib:searchPret>\r
         <refpret>?</refpret>\r
      </bib:searchPret>\r
   </soapenv:Body>\r
</soapenv:Envelope>]]></con:request><con:wsaConfig mustUnderstand="NONE" version="200508" action="http://biblio.com/BibliothequeServices/searchPretRequest"/></con:call></con:operation><con:operation id="be225b9e-4b63-4eed-adb1-5527357aa9a8" isOneWay="false" action="" name="updatePret" bindingOperationName="updatePret" type="Request-Response" inputName="" receivesAttachments="false" sendsAttachments="false" anonymous="optional"><con:settings/><con:call id="8ccff7db-474f-4982-b1a1-21dc2d2925dc" name="Request 1"><con:settings/><con:encoding>UTF-8</con:encoding><con:endpoint>http://localhost:8084/bibliotheque/bibliothequeB</con:endpoint><con:request><![CDATA[<soapenv:Envelope xmlns:soapenv="http://schemas.xmlsoap.org/soap/envelope/" xmlns:bib="http://biblio.com/">\r
   <soapenv:Header/>\r
   <soapenv:Body>\r
      <bib:updatePret>\r
         <!--Optional:-->\r
         <dureepret>?</dureepret>\r
         <prolonger>?</prolonger>\r
         <cloturationpret>?</cloturationpret>\r
         <refpret>?</refpret>\r
      </bib:updatePret>\r
   </soapenv:Body>\r
</soapenv:Envelope>]]></con:request><con:wsaConfig mustUnderstand="NONE" version="200508" action="http://biblio.com/BibliothequeServices/updatePretRequest"/></con:call></con:operation></con:interface><con:properties/><con:wssContainer/><con:oAuth2ProfileContainer/><con:oAuth1ProfileContainer/></con:soapui-project>